citros_data_analysis/__init__.py
citros_data_analysis/data_access/__init__.py
citros_data_analysis/data_access/_gql_base.py
citros_data_analysis/data_access/_gql_cursor.py
citros_data_analysis/data_access/_pg_cursor.py
citros_data_analysis/data_access/_plotter.py
citros_data_analysis/data_access/_stat.py
citros_data_analysis/data_access/_util.py
citros_data_analysis/data_access/citros_db.py
citros_data_analysis/data_access/citros_dict.py
citros_data_analysis/data_access/references.py
citros_data_analysis/error_analysis/__init__.py
citros_data_analysis/error_analysis/citros_data.py
citros_data_analysis/error_analysis/citros_data_array.py
citros_data_analysis/error_analysis/citros_stat.py
citros_data_analysis/validation/__init__.py
citros_data_analysis/validation/validation.py
citros_data_analysis-0.9.1.dist-info/LICENSE.txt
citros_data_analysis-0.9.1.dist-info/METADATA
citros_data_analysis-0.9.1.dist-info/WHEEL
citros_data_analysis-0.9.1.dist-info/top_level.txt
citros_data_analysis-0.9.1.dist-info/RECORD
