Metadata-Version: 2.1
Name: citros-data-analysis
Version: 0.9.1
Summary: Package for data analysis
Home-page: https://github.com/lulav/citros_data_analysis
Author: Yalyalieva
Author-email: lidia@lulav.space
License: LICENSE.txt
Requires-Python: >=3.8
License-File: LICENSE.txt
Requires-Dist: numpy
Requires-Dist: pymongo
Requires-Dist: pandas
Requires-Dist: psycopg2-binary
Requires-Dist: matplotlib
Requires-Dist: scipy
Requires-Dist: scikit-learn
Requires-Dist: gmr
Requires-Dist: prettytable
Requires-Dist: termcolor
Requires-Dist: gql
Requires-Dist: pyjwt
Requires-Dist: requests
Requires-Dist: requests-toolbelt
